pyenzyme/__init__.py
pyenzyme/composer.py
pyenzyme/logging.py
pyenzyme/pretty.py
pyenzyme/rdf.py
pyenzyme/suite.py
pyenzyme/tabular.py
pyenzyme/tools.py
pyenzyme/widgets.py
pyenzyme/xmlutils.py
pyenzyme/equations/__init__.py
pyenzyme/equations/chem.py
pyenzyme/equations/math.py
pyenzyme/fetcher/__init__.py
pyenzyme/fetcher/chebi.py
pyenzyme/fetcher/pdb.py
pyenzyme/fetcher/pubchem.py
pyenzyme/fetcher/rhea.py
pyenzyme/fetcher/uniprot.py
pyenzyme/petab/__init__.py
pyenzyme/petab/baserow.py
pyenzyme/petab/conditions.py
pyenzyme/petab/io.py
pyenzyme/petab/measurements.py
pyenzyme/petab/observables.py
pyenzyme/petab/parameters.py
pyenzyme/petab/petab.py
pyenzyme/plotting/__init__.py
pyenzyme/plotting/interactive.py
pyenzyme/plotting/static.py
pyenzyme/sbml/__init__.py
pyenzyme/sbml/ldutils.py
pyenzyme/sbml/omex.py
pyenzyme/sbml/parser.py
pyenzyme/sbml/serializer.py
pyenzyme/sbml/utils.py
pyenzyme/sbml/validation.py
pyenzyme/sbml/versions/__init__.py
pyenzyme/sbml/versions/handler.py
pyenzyme/sbml/versions/v1.py
pyenzyme/sbml/versions/v2.py
pyenzyme/thinlayers/__init__.py
pyenzyme/thinlayers/base.py
pyenzyme/thinlayers/basico.py
pyenzyme/thinlayers/psyces.py
pyenzyme/v1/__init__.py
pyenzyme/v1/enzymeml/__init__.py
pyenzyme/v1/enzymeml/core/__init__.py
pyenzyme/v1/enzymeml/core/abstract_classes.py
pyenzyme/v1/enzymeml/core/complex.py
pyenzyme/v1/enzymeml/core/creator.py
pyenzyme/v1/enzymeml/core/enzymemlbase.py
pyenzyme/v1/enzymeml/core/enzymemldocument.py
pyenzyme/v1/enzymeml/core/enzymereaction.py
pyenzyme/v1/enzymeml/core/exceptions.py
pyenzyme/v1/enzymeml/core/measurement.py
pyenzyme/v1/enzymeml/core/measurementData.py
pyenzyme/v1/enzymeml/core/ontology.py
pyenzyme/v1/enzymeml/core/protein.py
pyenzyme/v1/enzymeml/core/reactant.py
pyenzyme/v1/enzymeml/core/replicate.py
pyenzyme/v1/enzymeml/core/unitdef.py
pyenzyme/v1/enzymeml/core/utils.py
pyenzyme/v1/enzymeml/core/vessel.py
pyenzyme/v1/enzymeml/databases/__init__.py
pyenzyme/v1/enzymeml/databases/dataverse.py
pyenzyme-2.2.1.dist-info/METADATA
pyenzyme-2.2.1.dist-info/WHEEL
pyenzyme-2.2.1.dist-info/licenses/LICENSE
pyenzyme-2.2.1.dist-info/RECORD
