Metadata-Version: 2.4
Name: pyenzyme
Version: 2.2.1
Summary: A Python library for EnzymeML
Project-URL: Repository, https://github.com/EnzymeML/pyenzyme
Author-email: Jan Range <range.jan@web.de>
License: BSD-2-Clause
License-File: LICENSE
Requires-Python: <4,>=3.11
Requires-Dist: bokeh<4,>=3.7.3
Requires-Dist: dill<0.5.0,>=0.3.9
Requires-Dist: fastobo<0.14,>=0.13.0
Requires-Dist: httpx>=0.27
Requires-Dist: joblib<2,>=1.5.0
Requires-Dist: loguru<0.8,>=0.7.2
Requires-Dist: matplotlib<4,>=3.10
Requires-Dist: mdmodels<0.3,>=0.2.4
Requires-Dist: pandas>=2.0.0
Requires-Dist: pydantic-xml<3,>=2.17.0
Requires-Dist: pymetadata<0.6,>=0.5.3
Requires-Dist: python-libsbml<6,>=5.20.2
Requires-Dist: rdflib==7.0.0
Requires-Dist: rich<14,>=13.7.1
Requires-Dist: sympy<2,>=1.12.1
